dc_converter_tof-0.1.6.dist-info/METADATA
dc_converter_tof-0.1.6.dist-info/WHEEL
dc_converter_tof-0.1.6.dist-info/license_files/LICENSE.txt
dc_converter.libs/libunistring-9c28d595.so.2
dc_converter.libs/liblber-2-a862fafa.5.so.0
dc_converter.libs/libnettle-2d3bda6c.so.8
dc_converter.libs/libdav1d-eb4b11f1.so.5
dc_converter.libs/libdfalt-c7b3211a.so.0
dc_converter.libs/libfygm-98d9deae.so.0
dc_converter.libs/libkrb5support-58262db1.so.0
dc_converter.libs/libIlmImf-2_5-7155da24.so.25
dc_converter.libs/libzstd-5df4f4df.so.1
dc_converter.libs/libicudata-c1404396.so.70
dc_converter.libs/libbz2-5e516f77.so.1.0
dc_converter.libs/libblosc-1a5323ad.so.1
dc_converter.libs/libmysqlclient-a0fcd5a5.so.21
dc_converter.libs/libgnutls-31890d4c.so.30
dc_converter.libs/libminizip-fbdca10d.so.1
dc_converter.libs/libqhull_r-e92ac43c.so.8.0
dc_converter.libs/librttopo-6f9dbbad.so.1
dc_converter.libs/librtmp-2401c4fc.so.1
dc_converter.libs/libnghttp2-fdcf1344.so.14
dc_converter.libs/libarpack-268a7ad4.so.2
dc_converter.libs/libidn2-1420c60a.so.0
dc_converter.libs/libplc4-a97220af.so
dc_converter.libs/libicuuc-4683f362.so.70
dc_converter.libs/libgdcmjpeg16-682d45b4.so.3.0
dc_converter.libs/libsasl2-344870a9.so.2
dc_converter.libs/libcrypto-b1e52613.so.3
dc_converter.libs/libcurl-b23673f6.so.4
dc_converter.libs/libaom-1d6fe4ba.so.3
dc_converter.libs/libgeos_c-89378a4b.so.1
dc_converter.libs/libhdf5_serial-12e4461a.so.103
dc_converter.libs/libk5crypto-c7702e97.so.3
dc_converter.libs/libnetcdf-729d28c6.so.19
dc_converter.libs/libgdal-67fc9462.so.30
dc_converter.libs/libkmlengine-cab7ab5e.so.1
dc_converter.libs/libhogweed-47d56894.so.6
dc_converter.libs/libkeyutils-ad20d5fb.so.1
dc_converter.libs/libssh-5fff0a1d.so.4
dc_converter.libs/libtasn1-02557ad1.so.6
dc_converter.libs/libIlmThread-2_5-8f344396.so.25
dc_converter.libs/libIex-2_5-c16c5aa2.so.25
dc_converter.libs/libltdl-98bcf1a3.so.7
dc_converter.libs/libfreetype-ccc6ae91.so.6
dc_converter.libs/libgdcmMSFF-54484fd8.so.3.0
dc_converter.libs/libnss3-cb826113.so
dc_converter.libs/libx265-a72e1820.so.199
dc_converter.libs/libsuperlu-17cfc126.so.5
dc_converter_tof-0.1.6.dist-info/RECORD
